pyzu/__init__.py
pyzu/constants.py
pyzu/pyzu.py
pyzu-0.1.4.dist-info/LICENSE.txt
pyzu-0.1.4.dist-info/METADATA
pyzu-0.1.4.dist-info/RECORD
pyzu-0.1.4.dist-info/WHEEL
pyzu-0.1.4.dist-info/top_level.txt
