Metadata-Version: 2.1
Name: pyzu
Version: 0.1.4
Summary: Library to work with Open Graph metadata
Home-page: https://github.com/chason/pyzu
Author: Chason Chaffin
Author-email: chason@gmail.com
License: UNKNOWN
Keywords: opengraph opengraph-data rdfa rdflib
Platform: UNKNOWN
Classifier: Development Status :: 3 - Alpha
Classifier: Intended Audience :: Developers
Classifier: Topic :: Software Development :: Libraries
Classifier: License :: OSI Approved :: MIT License
Classifier: Programming Language :: Python :: 3
Classifier: Programming Language :: Python :: 3.6
Requires-Python: >=3.6
Provides-Extra: dev
Provides-Extra: test
Requires-Dist: requests
Requires-Dist: rdflib
Requires-Dist: html5lib
Provides-Extra: dev
Requires-Dist: bumpversion; extra == 'dev'
Requires-Dist: black; extra == 'dev'
Provides-Extra: test
Requires-Dist: pytest (>=3.5); extra == 'test'
Requires-Dist: coverage; extra == 'test'
Requires-Dist: coveralls; extra == 'test'
Requires-Dist: pytest-cov; extra == 'test'
Requires-Dist: pytest-mypy; extra == 'test'
Requires-Dist: pytest-flake8; extra == 'test'
